LICENSE
MANIFEST.in
README.md
setup.py
flybirds/__init__.py
flybirds/launcher.py
flybirds.egg-info/PKG-INFO
flybirds.egg-info/SOURCES.txt
flybirds.egg-info/dependency_links.txt
flybirds.egg-info/entry_points.txt
flybirds.egg-info/requires.txt
flybirds.egg-info/top_level.txt
flybirds/cli/__init__.py
flybirds/cli/__main__.py
flybirds/cli/create_project.py
flybirds/cli/parse_args.py
flybirds/core/__init__.py
flybirds/core/config_manage.py
flybirds/core/exceptions.py
flybirds/core/global_context.py
flybirds/core/global_resource.py
flybirds/core/script_config.py
flybirds/core/tag_expression.py
flybirds/core/driver/__init__.py
flybirds/core/driver/app.py
flybirds/core/driver/device.py
flybirds/core/driver/element.py
flybirds/core/driver/page.py
flybirds/core/driver/screen.py
flybirds/core/driver/ui_driver.py
flybirds/core/dsl/__init__.py
flybirds/core/dsl/globalization/__init__.py
flybirds/core/dsl/globalization/i18n.py
flybirds/core/dsl/hook/__init__.py
flybirds/core/dsl/hook/control_hook.py
flybirds/core/dsl/step/__init__.py
flybirds/core/dsl/step/app.py
flybirds/core/dsl/step/common.py
flybirds/core/dsl/step/device.py
flybirds/core/dsl/step/element.py
flybirds/core/dsl/step/page.py
flybirds/core/dsl/step/request.py
flybirds/core/dsl/step/step_loader.py
flybirds/core/extend/__init__.py
flybirds/core/extend/step.py
flybirds/core/launch_cycle/__init__.py
flybirds/core/launch_cycle/run_manage.py
flybirds/core/launch_cycle/chain/__init__.py
flybirds/core/launch_cycle/chain/launch_init.py
flybirds/core/launch_cycle/chain/load_hook_pkg.py
flybirds/core/launch_cycle/chain/package_finder.py
flybirds/core/launch_cycle/chain/report.py
flybirds/core/plugin/__init__.py
flybirds/core/plugin/life_cycle.py
flybirds/core/plugin/loader.py
flybirds/core/plugin/plugin_manager.py
flybirds/core/plugin/plugin_proxy.py
flybirds/core/plugin/event/__init__.py
flybirds/core/plugin/event/active_tag.py
flybirds/core/plugin/event/app_prepare.py
flybirds/core/plugin/event/config.py
flybirds/core/plugin/event/device_prepare.py
flybirds/core/plugin/event/driver_func_hook.py
flybirds/core/plugin/event/feature.py
flybirds/core/plugin/event/file_prepare.py
flybirds/core/plugin/event/run.py
