Metadata-Version: 1.2
Name: flybirds
Version: 0.7.0
Summary: BDD-driven natural language automated testing framework
Home-page: https://github.com/ctripcorp/flybirds
Author: trip_flight
Author-email: flybirds_support@trip.com
License: MIT license
Keywords: automation,automated-test,bdd,framework,android,ios,behave
Platform: UNKNOWN
Classifier: Programming Language :: Python :: 3.8
Classifier: Programming Language :: Python :: 3.9
Classifier: Programming Language :: Python :: 3.10
Requires-Python: >=3.8, <3.11
